runthered/push_api.py
runthered/__init__.py
runthered/http_gateway.py
runthered_python-1.0.0.dist-info/METADATA
runthered_python-1.0.0.dist-info/top_level.txt
runthered_python-1.0.0.dist-info/RECORD
runthered_python-1.0.0.dist-info/DESCRIPTION.rst
runthered_python-1.0.0.dist-info/WHEEL
runthered_python-1.0.0.dist-info/metadata.json
