Metadata-Version: 2.0
Name: runthered-python
Version: 1.0.0
Summary: Run The Red Python API wrapper library
Home-page: http://www.runthered.com/
Author: Run The Red
Author-email: support@runthered.com
License: MIT
Keywords: runthered,rtr
Platform: UNKNOWN
Classifier: Development Status :: 3 - Alpha
Classifier: Topic :: Software Development :: Libraries :: Python Modules
Classifier: License :: OSI Approved :: MIT License
Classifier: Programming Language :: Python :: 2
Classifier: Programming Language :: Python :: 2.6
Classifier: Programming Language :: Python :: 2.7
Classifier: Programming Language :: Python :: 3
Classifier: Programming Language :: Python :: 3.2
Classifier: Programming Language :: Python :: 3.3
Classifier: Programming Language :: Python :: 3.4
